kiki/__init__.py
kiki/kiki.py
kiki/pdf_handler.py
kiki/utils.py
kiki-1.0.1.dist-info/LICENSE.txt
kiki-1.0.1.dist-info/METADATA
kiki-1.0.1.dist-info/WHEEL
kiki-1.0.1.dist-info/entry_points.txt
kiki-1.0.1.dist-info/top_level.txt
kiki-1.0.1.dist-info/RECORD
