Metadata-Version: 2.1
Name: kiki
Version: 1.0.1
Summary: pdf text-to-speech
Home-page: https://github.com/VijayStroup/Kiki
Author: Vijay Stroup
Author-email: vijay@vijaystroup.com
License: UNKNOWN
Platform: UNKNOWN
Classifier: Programming Language :: Python :: 3
Classifier: License :: OSI Approved :: MIT License
Classifier: Operating System :: OS Independent
Requires-Dist: PyPDF2 (==1.26.0)
Requires-Dist: beautifulsoup4 (==4.9.3)
Requires-Dist: certifi (==2020.6.20)
Requires-Dist: chardet (==3.0.4)
Requires-Dist: click (==7.1.2)
Requires-Dist: gTTS-token (==1.1.3)
Requires-Dist: gTTS (==2.1.1)
Requires-Dist: idna (==2.10)
Requires-Dist: requests (==2.24.0)
Requires-Dist: six (==1.15.0)
Requires-Dist: soupsieve (==2.0.1)
Requires-Dist: typer (==0.3.2)
Requires-Dist: urllib3 (==1.25.10)
